fms_hf_tuning-3.1.0.dist-info/licenses/LICENSE
tuning/__init__.py
tuning/_version.py
tuning/sft_trainer.py
tuning/config/__init__.py
tuning/config/configs.py
tuning/config/peft_config.py
tuning/config/tracker_configs.py
tuning/config/acceleration_configs/__init__.py
tuning/config/acceleration_configs/acceleration_framework_config.py
tuning/config/acceleration_configs/attention_and_distributed_packing.py
tuning/config/acceleration_configs/callbacks.py
tuning/config/acceleration_configs/fast_moe.py
tuning/config/acceleration_configs/fused_ops_and_kernels.py
tuning/config/acceleration_configs/odm.py
tuning/config/acceleration_configs/quantized_lora_config.py
tuning/config/acceleration_configs/utils.py
tuning/data/__init__.py
tuning/data/collators.py
tuning/data/data_config.py
tuning/data/data_handlers.py
tuning/data/data_preprocessing_utils.py
tuning/data/data_processors.py
tuning/data/setup_dataprocessor.py
tuning/data/tokenizer_utils.py
tuning/data/utils.py
tuning/trackers/__init__.py
tuning/trackers/aimstack_tracker.py
tuning/trackers/clearml_tracker.py
tuning/trackers/filelogging_tracker.py
tuning/trackers/hf_resource_scanner_tracker.py
tuning/trackers/mlflow_tracker.py
tuning/trackers/tracker.py
tuning/trackers/tracker_factory.py
tuning/trainercontroller/__init__.py
tuning/trainercontroller/callback.py
tuning/trainercontroller/control.py
tuning/trainercontroller/patience.py
tuning/trainercontroller/controllermetrics/__init__.py
tuning/trainercontroller/controllermetrics/eval_metrics.py
tuning/trainercontroller/controllermetrics/history_based_metrics.py
tuning/trainercontroller/controllermetrics/loss.py
tuning/trainercontroller/controllermetrics/metrics.yaml
tuning/trainercontroller/controllermetrics/metricshandler.py
tuning/trainercontroller/controllermetrics/per_process_state.py
tuning/trainercontroller/controllermetrics/trainingstate.py
tuning/trainercontroller/operations/__init__.py
tuning/trainercontroller/operations/hfcontrols.py
tuning/trainercontroller/operations/logcontrol.py
fms_hf_tuning-3.1.0.dist-info/METADATA
fms_hf_tuning-3.1.0.dist-info/WHEEL
fms_hf_tuning-3.1.0.dist-info/top_level.txt
fms_hf_tuning-3.1.0.dist-info/RECORD
