Metadata-Version: 2.4
Name: fms-hf-tuning
Version: 3.1.0
Summary: FMS HF Tuning
Author-email: Sukriti Sharma <sukriti.sharma4@ibm.com>, Anh Uong <anh.uong@ibm.com>
License-Expression: Apache-2.0
Project-URL: Homepage, https://github.com/foundation-model-stack/fms-hf-tuning
Project-URL: Repository, https://github.com/foundation-model-stack/fms-hf-tuning
Project-URL: Issues, https://github.com/foundation-model-stack/fms-hf-tuning/issues
Keywords: fms-hf-tuning,python,tuning
Classifier: Development Status :: 5 - Production/Stable
Classifier: Programming Language :: Python :: 3
Classifier: Programming Language :: Python :: 3.9
Classifier: Programming Language :: Python :: 3.10
Classifier: Programming Language :: Python :: 3.11
Classifier: Programming Language :: Python :: 3.12
Requires-Python: ~=3.9
License-File: LICENSE
Requires-Dist: numpy<2.2.0,>=1.26.4
Requires-Dist: accelerate<2.0.0,>=1.9.0
Requires-Dist: transformers<=4.55.4,>=4.55.0
Requires-Dist: torch<2.9.0,>2.7.0
Requires-Dist: sentencepiece<0.3,>=0.1.99
Requires-Dist: tokenizers<=0.22
Requires-Dist: tqdm<5.0,>=4.66.2
Requires-Dist: trl<0.20.0,>=0.19.1
Requires-Dist: peft==0.18.0rc0
Requires-Dist: datasets<5.0.0,>=4.0.0
Requires-Dist: simpleeval<2.0,>=0.9.13
Requires-Dist: pillow<12.0,>=11.0.0
Requires-Dist: kernels<=0.9.0
Provides-Extra: dev
Requires-Dist: wheel<1.0,>=0.42.0; extra == "dev"
Requires-Dist: packaging<25,>=23.2; extra == "dev"
Requires-Dist: ninja<2.0,>=1.11.1.1; extra == "dev"
Requires-Dist: scikit-learn<2.0,>=1.0; extra == "dev"
Requires-Dist: boto3<2.0,>=1.34; extra == "dev"
Provides-Extra: flash-attn
Requires-Dist: flash-attn>=2.8.3; extra == "flash-attn"
Provides-Extra: aim
Requires-Dist: aim<4.0,>=3.19.0; extra == "aim"
Provides-Extra: mlflow
Requires-Dist: mlflow; extra == "mlflow"
Provides-Extra: clearml
Requires-Dist: clearml==2.0.0; extra == "clearml"
Provides-Extra: fms-accel
Requires-Dist: fms-acceleration>=0.6.2; extra == "fms-accel"
Provides-Extra: gptq-dev
Requires-Dist: auto_gptq>0.4.2; extra == "gptq-dev"
Requires-Dist: optimum>=1.15.0; extra == "gptq-dev"
Provides-Extra: mamba
Requires-Dist: mamba_ssm[causal-conv1d]<3.0.0,>=2.0.0; extra == "mamba"
Provides-Extra: scanner-dev
Requires-Dist: HFResourceScanner>=0.1.0; extra == "scanner-dev"
Dynamic: license-file
